{
  "timestamp": "2022-06-01T11:55:00Z",
  "data": [
    {
      "id": "5a6c613fb31d13b4fb58357ef91449c3",
      "sport_key": "basketball_nba",
      "sport_title": "NBA",
      "commence_time": "2022-06-03T01:00:00Z",
      "home_team": "Golden State Warriors",
      "away_team": "Boston Celtics",
      "bookmakers": [
        {
          "key": "sugarhouse",
          "title": "SugarHouse",
          "last_update": "2022-06-01T11:48:39Z",
          "markets": [
            {
              "key": "totals",
              "last_update": "2022-06-01T11:48:39Z",
              "outcomes": [
                {
                  "name": "Over",
                  "price": -110,
                  "point": 212.5
                },
                {
                  "name": "Under",
                  "price": -112,
                  "point": 212.5
                }
              ]
            },
            {
              "key": "spreads",
              "last_update": "2022-06-01T11:48:39Z",
              "outcomes": [
                {
                  "name": "Boston Celtics",
                  "price": -114,
                  "point": 3.5
                },
                {
                  "name": "Golden State Warriors",
                  "price": -108,
                  "point": -3.5
                }
              ]
            },
            {
              "key": "h2h",
              "last_update": "2022-06-01T11:48:39Z",
              "outcomes": [
                {
                  "name": "Boston Celtics",
                  "price": 133
                },
                {
                  "name": "Golden State Warriors",
                  "price": -159
                }
              ]
            }
          ]
        },
        {
          "key": "unibet",
          "title": "Unibet",
          "last_update": "2022-06-01T11:45:47Z",
          "markets": [
            {
              "key": "spreads",
              "last_update": "2022-06-01T11:45:47Z",
              "outcomes": [
                {
                  "name": "Boston Celtics",
                  "price": -114,
                  "point": 3.5
                },
                {
                  "name": "Golden State Warriors",
                  "price": -108,
                  "point": -3.5
                }
              ]
            },
            {
              "key": "totals",
              "last_update": "2022-06-01T11:45:47Z",
              "outcomes": [
                {
                  "name": "Over",
                  "price": -110,
                  "point": 212.5
                },
                {
                  "name": "Under",
                  "price": -111,
                  "point": 212.5
                }
              ]
            },
            {
              "key": "h2h",
              "last_update": "2022-06-01T11:45:47Z",
              "outcomes": [
                {
                  "name": "Boston Celtics",
                  "price": 133
                },
                {
                  "name": "Golden State Warriors",
                  "price": -159
                }
              ]
            }
          ]
        },
        {
          "key": "williamhill_us",
          "title": "William Hill (US)",
          "last_update": "2022-06-01T11:48:47Z",
          "markets": [
            {
              "key": "spreads",
              "last_update": "2022-06-01T11:48:47Z",
              "outcomes": [
                {
                  "name": "Boston Celtics",
                  "price": -110,
                  "point": 3.5
                },
                {
                  "name": "Golden State Warriors",
                  "price": -110,
                  "point": -3.5
                }
              ]
            },
            {
              "key": "totals",
              "last_update": "2022-06-01T11:48:47Z",
              "outcomes": [
                {
                  "name": "Over",
                  "price": -110,
                  "point": 212.5
                },
                {
                  "name": "Under",
                  "price": -110,
                  "point": 212.5
                }
              ]
            },
            {
              "key": "h2h",
              "last_update": "2022-06-01T11:48:47Z",
              "outcomes": [
                {
                  "name": "Boston Celtics",
                  "price": 140
                },
                {
                  "name": "Golden State Warriors",
                  "price": -161
                }
              ]
            }
          ]
        },
        {
          "key": "betrivers",
          "title": "BetRivers",
          "last_update": "2022-06-01T11:45:41Z",
          "markets": [
            {
              "key": "totals",
              "last_update": "2022-06-01T11:45:41Z",
              "outcomes": [
                {
                  "name": "Over",
                  "price": -110,
                  "point": 212.5
                },
                {
                  "name": "Under",
                  "price": -112,
                  "point": 212.5
                }
              ]
            },
            {
              "key": "spreads",
              "last_update": "2022-06-01T11:45:41Z",
              "outcomes": [
                {
                  "name": "Boston Celtics",
                  "price": -114,
                  "point": 3.5
                },
                {
                  "name": "Golden State Warriors",
                  "price": -108,
                  "point": -3.5
                }
              ]
            },
            {
              "key": "h2h",
              "last_update": "2022-06-01T11:45:41Z",
              "outcomes": [
                {
                  "name": "Boston Celtics",
                  "price": 133
                },
                {
                  "name": "Golden State Warriors",
                  "price": -159
                }
              ]
            }
          ]
        },
        {
          "key": "twinspires",
          "title": "TwinSpires",
          "last_update": "2022-06-01T11:47:44Z",
          "markets": [
            {
              "key": "spreads",
              "last_update": "2022-06-01T11:47:44Z",
              "outcomes": [
                {
                  "name": "Boston Celtics",
                  "price": -114,
                  "point": 3.5
                },
                {
                  "name": "Golden State Warriors",
                  "price": -108,
                  "point": -3.5
                }
              ]
            },
            {
              "key": "totals",
              "last_update": "2022-06-01T11:47:44Z",
              "outcomes": [
                {
                  "name": "Over",
                  "price": -110,
                  "point": 212.5
                },
                {
                  "name": "Under",
                  "price": -112,
                  "point": 212.5
                }
              ]
            },
            {
              "key": "h2h",
              "last_update": "2022-06-01T11:47:44Z",
              "outcomes": [
                {
                  "name": "Boston Celtics",
                  "price": 133
                },
                {
                  "name": "Golden State Warriors",
                  "price": -159
                }
              ]
            }
          ]
        },
        {
          "key": "draftkings",
          "title": "DraftKings",
          "last_update": "2022-06-01T11:47:45Z",
          "markets": [
            {
              "key": "spreads",
              "last_update": "2022-06-01T11:47:45Z",
              "outcomes": [
                {
                  "name": "Boston Celtics",
                  "price": -105,
                  "point": 3.5
                },
                {
                  "name": "Golden State Warriors",
                  "price": -115,
                  "point": -3.5
                }
              ]
            },
            {
              "key": "totals",
              "last_update": "2022-06-01T11:47:45Z",
              "outcomes": [
                {
                  "name": "Over",
                  "price": -110,
                  "point": 212.5
                },
                {
                  "name": "Under",
                  "price": -110,
                  "point": 212.5
                }
              ]
            },
            {
              "key": "h2h",
              "last_update": "2022-06-01T11:47:45Z",
              "outcomes": [
                {
                  "name": "Boston Celtics",
                  "price": 140
                },
                {
                  "name": "Golden State Warriors",
                  "price": -161
                }
              ]
            }
          ]
        },
        {
          "key": "wynnbet",
          "title": "WynnBET",
          "last_update": "2022-06-01T11:46:11Z",
          "markets": [
            {
              "key": "totals",
              "last_update": "2022-06-01T11:46:11Z",
              "outcomes": [
                {
                  "name": "Over",
                  "price": -108,
                  "point": 212.0
                },
                {
                  "name": "Under",
                  "price": -108,
                  "point": 212.0
                }
              ]
            },
            {
              "key": "spreads",
              "last_update": "2022-06-01T11:46:11Z",
              "outcomes": [
                {
                  "name": "Boston Celtics",
                  "price": -108,
                  "point": 3.5
                },
                {
                  "name": "Golden State Warriors",
                  "price": -108,
                  "point": -3.5
                }
              ]
            },
            {
              "key": "h2h",
              "last_update": "2022-06-01T11:46:11Z",
              "outcomes": [
                {
                  "name": "Boston Celtics",
                  "price": 135
                },
                {
                  "name": "Golden State Warriors",
                  "price": -164
                }
              ]
            }
          ]
        },
        {
          "key": "betonlineag",
          "title": "BetOnline.ag",
          "last_update": "2022-06-01T11:45:44Z",
          "markets": [
            {
              "key": "spreads",
              "last_update": "2022-06-01T11:45:44Z",
              "outcomes": [
                {
                  "name": "Boston Celtics",
                  "price": -111,
                  "point": 3.5
                },
                {
                  "name": "Golden State Warriors",
                  "price": -111,
                  "point": -3.5
                }
              ]
            },
            {
              "key": "totals",
              "last_update": "2022-06-01T11:45:44Z",
              "outcomes": [
                {
                  "name": "Over",
                  "price": -111,
                  "point": 212.5
                },
                {
                  "name": "Under",
                  "price": -111,
                  "point": 212.5
                }
              ]
            },
            {
              "key": "h2h",
              "last_update": "2022-06-01T11:45:44Z",
              "outcomes": [
                {
                  "name": "Boston Celtics",
                  "price": 137
                },
                {
                  "name": "Golden State Warriors",
                  "price": -159
                }
              ]
            }
          ]
        },
        {
          "key": "barstool",
          "title": "Barstool Sportsbook",
          "last_update": "2022-06-01T11:48:31Z",
          "markets": [
            {
              "key": "spreads",
              "last_update": "2022-06-01T11:48:31Z",
              "outcomes": [
                {
                  "name": "Boston Celtics",
                  "price": -114,
                  "point": 3.5
                },
                {
                  "name": "Golden State Warriors",
                  "price": -108,
                  "point": -3.5
                }
              ]
            },
            {
              "key": "totals",
              "last_update": "2022-06-01T11:48:31Z",
              "outcomes": [
                {
                  "name": "Over",
                  "price": -110,
                  "point": 212.5
                },
                {
                  "name": "Under",
                  "price": -112,
                  "point": 212.5
                }
              ]
            },
            {
              "key": "h2h",
              "last_update": "2022-06-01T11:48:31Z",
              "outcomes": [
                {
                  "name": "Boston Celtics",
                  "price": 133
                },
                {
                  "name": "Golden State Warriors",
                  "price": -159
                }
              ]
            }
          ]
        },
        {
          "key": "bovada",
          "title": "Bovada",
          "last_update": "2022-06-01T11:47:29Z",
          "markets": [
            {
              "key": "totals",
              "last_update": "2022-06-01T11:47:29Z",
              "outcomes": [
                {
                  "name": "Over",
                  "price": -110,
                  "point": 212.5
                },
                {
                  "name": "Under",
                  "price": -110,
                  "point": 212.5
                }
              ]
            },
            {
              "key": "spreads",
              "last_update": "2022-06-01T11:47:29Z",
              "outcomes": [
                {
                  "name": "Boston Celtics",
                  "price": -105,
                  "point": 3.5
                },
                {
                  "name": "Golden State Warriors",
                  "price": -115,
                  "point": -3.5
                }
              ]
            },
            {
              "key": "h2h",
              "last_update": "2022-06-01T11:47:29Z",
              "outcomes": [
                {
                  "name": "Boston Celtics",
                  "price": 140
                },
                {
                  "name": "Golden State Warriors",
                  "price": -164
                }
              ]
            }
          ]
        },
        {
          "key": "foxbet",
          "title": "FOX Bet",
          "last_update": "2022-06-01T11:46:54Z",
          "markets": [
            {
              "key": "totals",
              "last_update": "2022-06-01T11:46:54Z",
              "outcomes": [
                {
                  "name": "Over",
                  "price": -118,
                  "point": 211.5
                },
                {
                  "name": "Under",
                  "price": 100,
                  "point": 211.5
                }
              ]
            },
            {
              "key": "spreads",
              "last_update": "2022-06-01T11:46:54Z",
              "outcomes": [
                {
                  "name": "Boston Celtics",
                  "price": -118,
                  "point": 4.0
                },
                {
                  "name": "Golden State Warriors",
                  "price": 100,
                  "point": -4.0
                }
              ]
            },
            {
              "key": "h2h",
              "last_update": "2022-06-01T11:46:54Z",
              "outcomes": [
                {
                  "name": "Boston Celtics",
                  "price": 130
                },
                {
                  "name": "Golden State Warriors",
                  "price": -175
                }
              ]
            }
          ]
        },
        {
          "key": "lowvig",
          "title": "LowVig.ag",
          "last_update": "2022-06-01T11:44:45Z",
          "markets": [
            {
              "key": "spreads",
              "last_update": "2022-06-01T11:44:45Z",
              "outcomes": [
                {
                  "name": "Boston Celtics",
                  "price": -105,
                  "point": 3.5
                },
                {
                  "name": "Golden State Warriors",
                  "price": -105,
                  "point": -3.5
                }
              ]
            },
            {
              "key": "totals",
              "last_update": "2022-06-01T11:44:45Z",
              "outcomes": [
                {
                  "name": "Over",
                  "price": -105,
                  "point": 212.5
                },
                {
                  "name": "Under",
                  "price": -105,
                  "point": 212.5
                }
              ]
            },
            {
              "key": "h2h",
              "last_update": "2022-06-01T11:44:45Z",
              "outcomes": [
                {
                  "name": "Boston Celtics",
                  "price": 137
                },
                {
                  "name": "Golden State Warriors",
                  "price": -156
                }
              ]
            }
          ]
        },
        {
          "key": "mybookieag",
          "title": "MyBookie.ag",
          "last_update": "2022-06-01T11:48:28Z",
          "markets": [
            {
              "key": "totals",
              "last_update": "2022-06-01T11:48:28Z",
              "outcomes": [
                {
                  "name": "Over",
                  "price": -110,
                  "point": 212.0
                },
                {
                  "name": "Under",
                  "price": -110,
                  "point": 212.0
                }
              ]
            },
            {
              "key": "spreads",
              "last_update": "2022-06-01T11:48:28Z",
              "outcomes": [
                {
                  "name": "Boston Celtics",
                  "price": -115,
                  "point": 4.0
                },
                {
                  "name": "Golden State Warriors",
                  "price": -105,
                  "point": -4.0
                }
              ]
            },
            {
              "key": "h2h",
              "last_update": "2022-06-01T11:48:28Z",
              "outcomes": [
                {
                  "name": "Boston Celtics",
                  "price": 145
                },
                {
                  "name": "Golden State Warriors",
                  "price": -175
                }
              ]
            }
          ]
        },
        {
          "key": "pointsbetus",
          "title": "PointsBet (US)",
          "last_update": "2022-06-01T11:49:15Z",
          "markets": [
            {
              "key": "spreads",
              "last_update": "2022-06-01T11:49:15Z",
              "outcomes": [
                {
                  "name": "Boston Celtics",
                  "price": -110,
                  "point": 3.5
                },
                {
                  "name": "Golden State Warriors",
                  "price": -110,
                  "point": -3.5
                }
              ]
            },
            {
              "key": "totals",
              "last_update": "2022-06-01T11:49:15Z",
              "outcomes": [
                {
                  "name": "Over",
                  "price": -110,
                  "point": 212.5
                },
                {
                  "name": "Under",
                  "price": -110,
                  "point": 212.5
                }
              ]
            },
            {
              "key": "h2h",
              "last_update": "2022-06-01T11:49:15Z",
              "outcomes": [
                {
                  "name": "Boston Celtics",
                  "price": 140
                },
                {
                  "name": "Golden State Warriors",
                  "price": -169
                }
              ]
            }
          ]
        },
        {
          "key": "betfair",
          "title": "Betfair",
          "last_update": "2022-06-01T11:49:00Z",
          "markets": [
            {
              "key": "h2h_lay",
              "last_update": "2022-06-01T11:49:00Z",
              "outcomes": [
                {
                  "name": "Boston Celtics",
                  "price": 160
                },
                {
                  "name": "Golden State Warriors",
                  "price": -149
                }
              ]
            },
            {
              "key": "h2h",
              "last_update": "2022-06-01T11:49:00Z",
              "outcomes": [
                {
                  "name": "Boston Celtics",
                  "price": 146
                },
                {
                  "name": "Golden State Warriors",
                  "price": -159
                }
              ]
            }
          ]
        },
        {
          "key": "betmgm",
          "title": "BetMGM",
          "last_update": "2022-06-01T11:47:04Z",
          "markets": [
            {
              "key": "totals",
              "last_update": "2022-06-01T11:47:04Z",
              "outcomes": [
                {
                  "name": "Over",
                  "price": -110,
                  "point": 212.5
                },
                {
                  "name": "Under",
                  "price": -110,
                  "point": 212.5
                }
              ]
            },
            {
              "key": "spreads",
              "last_update": "2022-06-01T11:47:04Z",
              "outcomes": [
                {
                  "name": "Boston Celtics",
                  "price": -110,
                  "point": 3.5
                },
                {
                  "name": "Golden State Warriors",
                  "price": -110,
                  "point": -3.5
                }
              ]
            }
          ]
        },
        {
          "key": "fanduel",
          "title": "FanDuel",
          "last_update": "2022-06-01T11:48:22Z",
          "markets": [
            {
              "key": "spreads",
              "last_update": "2022-06-01T11:48:22Z",
              "outcomes": [
                {
                  "name": "Boston Celtics",
                  "price": -110,
                  "point": 4.0
                },
                {
                  "name": "Golden State Warriors",
                  "price": -110,
                  "point": -4.0
                }
              ]
            },
            {
              "key": "totals",
              "last_update": "2022-06-01T11:48:22Z",
              "outcomes": [
                {
                  "name": "Over",
                  "price": -110,
                  "point": 212.5
                },
                {
                  "name": "Under",
                  "price": -110,
                  "point": 212.5
                }
              ]
            },
            {
              "key": "h2h",
              "last_update": "2022-06-01T11:48:22Z",
              "outcomes": [
                {
                  "name": "Boston Celtics",
                  "price": 142
                },
                {
                  "name": "Golden State Warriors",
                  "price": -167
                }
              ]
            }
          ]
        },
        {
          "key": "gtbets",
          "title": "GTbets",
          "last_update": "2022-06-01T11:46:06Z",
          "markets": [
            {
              "key": "spreads",
              "last_update": "2022-06-01T11:46:06Z",
              "outcomes": [
                {
                  "name": "Boston Celtics",
                  "price": -109,
                  "point": 3.5
                },
                {
                  "name": "Golden State Warriors",
                  "price": -109,
                  "point": -3.5
                }
              ]
            },
            {
              "key": "totals",
              "last_update": "2022-06-01T11:46:06Z",
              "outcomes": [
                {
                  "name": "Over",
                  "price": -109,
                  "point": 212.5
                },
                {
                  "name": "Under",
                  "price": -109,
                  "point": 212.5
                }
              ]
            },
            {
              "key": "h2h",
              "last_update": "2022-06-01T11:46:06Z",
              "outcomes": [
                {
                  "name": "Boston Celtics",
                  "price": 145
                },
                {
                  "name": "Golden State Warriors",
                  "price": -164
                }
              ]
            }
          ]
        },
        {
          "key": "betus",
          "title": "BetUS",
          "last_update": "2022-06-01T11:48:12Z",
          "markets": [
            {
              "key": "spreads",
              "last_update": "2022-06-01T11:48:12Z",
              "outcomes": [
                {
                  "name": "Boston Celtics",
                  "price": -110,
                  "point": 3.5
                },
                {
                  "name": "Golden State Warriors",
                  "price": -110,
                  "point": -3.5
                }
              ]
            },
            {
              "key": "totals",
              "last_update": "2022-06-01T11:48:12Z",
              "outcomes": [
                {
                  "name": "Over",
                  "price": -110,
                  "point": 212.5
                },
                {
                  "name": "Under",
                  "price": -110,
                  "point": 212.5
                }
              ]
            },
            {
              "key": "h2h",
              "last_update": "2022-06-01T11:48:12Z",
              "outcomes": [
                {
                  "name": "Boston Celtics",
                  "price": 140
                },
                {
                  "name": "Golden State Warriors",
                  "price": -161
                }
              ]
            }
          ]
        }
      ]
    }
  ]
}