{
  "timestamp": "2025-06-16T11:55:37Z",
  "previous_timestamp": "2025-06-16T11:50:37Z",
  "next_timestamp": "2025-06-16T12:00:37Z",
  "data": [
    {
      "id": "aa4b036621875e4870ae8bdbca0dfc50",
      "sport_key": "basketball_nba",
      "sport_title": "NBA",
      "commence_time": "2025-06-17T00:35:00Z",
      "home_team": "Oklahoma City Thunder",
      "away_team": "Indiana Pacers",
      "bookmakers": [
        {
          "key": "draftkings",
          "title": "DraftKings",
          "last_update": "2025-06-16T11:55:10Z",
          "markets": [
            {
              "key": "h2h",
              "last_update": "2025-06-16T11:55:10Z",
              "outcomes": [
                {
                  "name": "Indiana Pacers",
                  "price": 320
                },
                {
                  "name": "Oklahoma City Thunder",
                  "price": -410
                }
              ]
            },
            {
              "key": "spreads",
              "last_update": "2025-06-16T11:55:10Z",
              "outcomes": [
                {
                  "name": "Indiana Pacers",
                  "price": -112,
                  "point": 9.5
                },
                {
                  "name": "Oklahoma City Thunder",
                  "price": -108,
                  "point": -9.5
                }
              ]
            },
            {
              "key": "totals",
              "last_update": "2025-06-16T11:55:10Z",
              "outcomes": [
                {
                  "name": "Over",
                  "price": -110,
                  "point": 225.0
                },
                {
                  "name": "Under",
                  "price": -110,
                  "point": 225.0
                }
              ]
            }
          ]
        },
        {
          "key": "fanduel",
          "title": "FanDuel",
          "last_update": "2025-06-16T11:55:03Z",
          "markets": [
            {
              "key": "h2h",
              "last_update": "2025-06-16T11:55:03Z",
              "outcomes": [
                {
                  "name": "Indiana Pacers",
                  "price": 320
                },
                {
                  "name": "Oklahoma City Thunder",
                  "price": -405
                }
              ]
            },
            {
              "key": "spreads",
              "last_update": "2025-06-16T11:55:03Z",
              "outcomes": [
                {
                  "name": "Indiana Pacers",
                  "price": -112,
                  "point": 9.5
                },
                {
                  "name": "Oklahoma City Thunder",
                  "price": -108,
                  "point": -9.5
                }
              ]
            },
            {
              "key": "totals",
              "last_update": "2025-06-16T11:55:03Z",
              "outcomes": [
                {
                  "name": "Over",
                  "price": -110,
                  "point": 224.5
                },
                {
                  "name": "Under",
                  "price": -110,
                  "point": 224.5
                }
              ]
            }
          ]
        },
        {
          "key": "betmgm",
          "title": "BetMGM",
          "last_update": "2025-06-16T11:54:48Z",
          "markets": [
            {
              "key": "h2h",
              "last_update": "2025-06-16T11:54:48Z",
              "outcomes": [
                {
                  "name": "Indiana Pacers",
                  "price": 333
                },
                {
                  "name": "Oklahoma City Thunder",
                  "price": -450
                }
              ]
            },
            {
              "key": "spreads",
              "last_update": "2025-06-16T11:54:48Z",
              "outcomes": [
                {
                  "name": "Indiana Pacers",
                  "price": -110,
                  "point": 9.5
                },
                {
                  "name": "Oklahoma City Thunder",
                  "price": -110,
                  "point": -9.5
                }
              ]
            },
            {
              "key": "totals",
              "last_update": "2025-06-16T11:54:48Z",
              "outcomes": [
                {
                  "name": "Over",
                  "price": -110,
                  "point": 224.5
                },
                {
                  "name": "Under",
                  "price": -110,
                  "point": 224.5
                }
              ]
            }
          ]
        },
        {
          "key": "betonlineag",
          "title": "BetOnline.ag",
          "last_update": "2025-06-16T11:54:52Z",
          "markets": [
            {
              "key": "h2h",
              "last_update": "2025-06-16T11:54:52Z",
              "outcomes": [
                {
                  "name": "Indiana Pacers",
                  "price": 320
                },
                {
                  "name": "Oklahoma City Thunder",
                  "price": -405
                }
              ]
            },
            {
              "key": "spreads",
              "last_update": "2025-06-16T11:54:52Z",
              "outcomes": [
                {
                  "name": "Indiana Pacers",
                  "price": -110,
                  "point": 9.5
                },
                {
                  "name": "Oklahoma City Thunder",
                  "price": -110,
                  "point": -9.5
                }
              ]
            },
            {
              "key": "totals",
              "last_update": "2025-06-16T11:54:52Z",
              "outcomes": [
                {
                  "name": "Over",
                  "price": -110,
                  "point": 224.5
                },
                {
                  "name": "Under",
                  "price": -110,
                  "point": 224.5
                }
              ]
            }
          ]
        },
        {
          "key": "lowvig",
          "title": "LowVig.ag",
          "last_update": "2025-06-16T11:54:52Z",
          "markets": [
            {
              "key": "h2h",
              "last_update": "2025-06-16T11:54:52Z",
              "outcomes": [
                {
                  "name": "Indiana Pacers",
                  "price": 325
                },
                {
                  "name": "Oklahoma City Thunder",
                  "price": -400
                }
              ]
            },
            {
              "key": "spreads",
              "last_update": "2025-06-16T11:54:52Z",
              "outcomes": [
                {
                  "name": "Indiana Pacers",
                  "price": -106,
                  "point": 9.5
                },
                {
                  "name": "Oklahoma City Thunder",
                  "price": -106,
                  "point": -9.5
                }
              ]
            },
            {
              "key": "totals",
              "last_update": "2025-06-16T11:54:52Z",
              "outcomes": [
                {
                  "name": "Over",
                  "price": -107,
                  "point": 224.5
                },
                {
                  "name": "Under",
                  "price": -107,
                  "point": 224.5
                }
              ]
            }
          ]
        },
        {
          "key": "betrivers",
          "title": "BetRivers",
          "last_update": "2025-06-16T11:55:22Z",
          "markets": [
            {
              "key": "h2h",
              "last_update": "2025-06-16T11:55:22Z",
              "outcomes": [
                {
                  "name": "Indiana Pacers",
                  "price": 310
                },
                {
                  "name": "Oklahoma City Thunder",
                  "price": -400
                }
              ]
            },
            {
              "key": "spreads",
              "last_update": "2025-06-16T11:55:22Z",
              "outcomes": [
                {
                  "name": "Indiana Pacers",
                  "price": -110,
                  "point": 9.5
                },
                {
                  "name": "Oklahoma City Thunder",
                  "price": -113,
                  "point": -9.5
                }
              ]
            },
            {
              "key": "totals",
              "last_update": "2025-06-16T11:55:22Z",
              "outcomes": [
                {
                  "name": "Over",
                  "price": -112,
                  "point": 224.5
                },
                {
                  "name": "Under",
                  "price": -112,
                  "point": 224.5
                }
              ]
            }
          ]
        },
        {
          "key": "williamhill_us",
          "title": "Caesars",
          "last_update": "2025-06-16T11:54:48Z",
          "markets": [
            {
              "key": "h2h",
              "last_update": "2025-06-16T11:54:48Z",
              "outcomes": [
                {
                  "name": "Indiana Pacers",
                  "price": 328
                },
                {
                  "name": "Oklahoma City Thunder",
                  "price": -430
                }
              ]
            },
            {
              "key": "spreads",
              "last_update": "2025-06-16T11:54:48Z",
              "outcomes": [
                {
                  "name": "Indiana Pacers",
                  "price": -110,
                  "point": 9.5
                },
                {
                  "name": "Oklahoma City Thunder",
                  "price": -110,
                  "point": -9.5
                }
              ]
            },
            {
              "key": "totals",
              "last_update": "2025-06-16T11:54:48Z",
              "outcomes": [
                {
                  "name": "Over",
                  "price": -110,
                  "point": 224.5
                },
                {
                  "name": "Under",
                  "price": -110,
                  "point": 224.5
                }
              ]
            }
          ]
        },
        {
          "key": "bovada",
          "title": "Bovada",
          "last_update": "2025-06-16T11:55:31Z",
          "markets": [
            {
              "key": "h2h",
              "last_update": "2025-06-16T11:55:31Z",
              "outcomes": [
                {
                  "name": "Indiana Pacers",
                  "price": 305
                },
                {
                  "name": "Oklahoma City Thunder",
                  "price": -410
                }
              ]
            },
            {
              "key": "spreads",
              "last_update": "2025-06-16T11:55:31Z",
              "outcomes": [
                {
                  "name": "Indiana Pacers",
                  "price": -115,
                  "point": 9.5
                },
                {
                  "name": "Oklahoma City Thunder",
                  "price": -105,
                  "point": -9.5
                }
              ]
            },
            {
              "key": "totals",
              "last_update": "2025-06-16T11:55:31Z",
              "outcomes": [
                {
                  "name": "Over",
                  "price": -115,
                  "point": 225.0
                },
                {
                  "name": "Under",
                  "price": -105,
                  "point": 225.0
                }
              ]
            }
          ]
        },
        {
          "key": "fanatics",
          "title": "Fanatics",
          "last_update": "2025-06-16T11:55:08Z",
          "markets": [
            {
              "key": "h2h",
              "last_update": "2025-06-16T11:55:08Z",
              "outcomes": [
                {
                  "name": "Indiana Pacers",
                  "price": 310
                },
                {
                  "name": "Oklahoma City Thunder",
                  "price": -400
                }
              ]
            },
            {
              "key": "spreads",
              "last_update": "2025-06-16T11:55:08Z",
              "outcomes": [
                {
                  "name": "Indiana Pacers",
                  "price": -110,
                  "point": 9.5
                },
                {
                  "name": "Oklahoma City Thunder",
                  "price": -110,
                  "point": -9.5
                }
              ]
            },
            {
              "key": "totals",
              "last_update": "2025-06-16T11:55:08Z",
              "outcomes": [
                {
                  "name": "Over",
                  "price": -110,
                  "point": 224.5
                },
                {
                  "name": "Under",
                  "price": -110,
                  "point": 224.5
                }
              ]
            }
          ]
        },
        {
          "key": "betus",
          "title": "BetUS",
          "last_update": "2025-06-16T11:55:27Z",
          "markets": [
            {
              "key": "h2h",
              "last_update": "2025-06-16T11:55:27Z",
              "outcomes": [
                {
                  "name": "Indiana Pacers",
                  "price": 338
                },
                {
                  "name": "Oklahoma City Thunder",
                  "price": -430
                }
              ]
            },
            {
              "key": "spreads",
              "last_update": "2025-06-16T11:55:27Z",
              "outcomes": [
                {
                  "name": "Indiana Pacers",
                  "price": -110,
                  "point": 9.5
                },
                {
                  "name": "Oklahoma City Thunder",
                  "price": -110,
                  "point": -9.5
                }
              ]
            },
            {
              "key": "totals",
              "last_update": "2025-06-16T11:55:27Z",
              "outcomes": [
                {
                  "name": "Over",
                  "price": -110,
                  "point": 224.5
                },
                {
                  "name": "Under",
                  "price": -110,
                  "point": 224.5
                }
              ]
            }
          ]
        }
      ]
    }
  ]
}