{
  "timestamp": "2021-11-10T11:55:00Z",
  "previous_timestamp": "2021-11-10T11:45:00Z",
  "next_timestamp": "2021-11-10T12:05:00Z",
  "data": [
    {
      "id": "c4acf0087c5c1c5773131790f1ded291",
      "sport_key": "basketball_nba",
      "sport_title": "NBA",
      "commence_time": "2021-12-25T17:00:00Z",
      "home_team": "New York Knicks",
      "away_team": "Atlanta Hawks"
    },
    {
      "id": "f710b144d576f85b196af94a143c40fb",
      "sport_key": "basketball_nba",
      "sport_title": "NBA",
      "commence_time": "2021-12-25T19:30:00Z",
      "home_team": "Milwaukee Bucks",
      "away_team": "Boston Celtics"
    },
    {
      "id": "de6765e3631b1f9b61396c7348e1ea9a",
      "sport_key": "basketball_nba",
      "sport_title": "NBA",
      "commence_time": "2021-12-25T22:00:00Z",
      "home_team": "Phoenix Suns",
      "away_team": "Golden State Warriors"
    },
    {
      "id": "927cafe41beb96b769c7f146fc52e957",
      "sport_key": "basketball_nba",
      "sport_title": "NBA",
      "commence_time": "2021-12-26T01:00:00Z",
      "home_team": "Los Angeles Lakers",
      "away_team": "Brooklyn Nets"
    },
    {
      "id": "87d85899740919564d9bce59814cb9e7",
      "sport_key": "basketball_nba",
      "sport_title": "NBA",
      "commence_time": "2021-12-26T03:30:00Z",
      "home_team": "Utah Jazz",
      "away_team": "Dallas Mavericks"
    },
    {
      "id": "f3dfc87bec58daee23a7359d65b4db6c",
      "sport_key": "basketball_nba",
      "sport_title": "NBA",
      "commence_time": "2021-11-11T00:10:00Z",
      "home_team": "Cleveland Cavaliers",
      "away_team": "Washington Wizards"
    },
    {
      "id": "185af0e8406014174202a0ff5e017e7a",
      "sport_key": "basketball_nba",
      "sport_title": "NBA",
      "commence_time": "2021-11-11T00:10:00Z",
      "home_team": "Orlando Magic",
      "away_team": "Brooklyn Nets"
    },
    {
      "id": "ad883075e5c00a18c59212004daea172",
      "sport_key": "basketball_nba",
      "sport_title": "NBA",
      "commence_time": "2021-11-11T00:40:00Z",
      "home_team": "New York Knicks",
      "away_team": "Milwaukee Bucks"
    },
    {
      "id": "16685afe664059f519c2dc3f5aff3c8d",
      "sport_key": "basketball_nba",
      "sport_title": "NBA",
      "commence_time": "2021-11-11T00:40:00Z",
      "home_team": "Boston Celtics",
      "away_team": "Toronto Raptors"
    },
    {
      "id": "cc8e0fc462122268d6facd89e52045dc",
      "sport_key": "basketball_nba",
      "sport_title": "NBA",
      "commence_time": "2021-11-11T01:10:00Z",
      "home_team": "Memphis Grizzlies",
      "away_team": "Charlotte Hornets"
    },
    {
      "id": "123a30461bea08401f1f17513314a396",
      "sport_key": "basketball_nba",
      "sport_title": "NBA",
      "commence_time": "2021-11-11T01:10:00Z",
      "home_team": "Chicago Bulls",
      "away_team": "Dallas Mavericks"
    },
    {
      "id": "6136cc687a4991466dbcf0ac969e266c",
      "sport_key": "basketball_nba",
      "sport_title": "NBA",
      "commence_time": "2021-11-11T01:40:00Z",
      "home_team": "San Antonio Spurs",
      "away_team": "Sacramento Kings"
    },
    {
      "id": "2b60b80facf672ac097309e134c492b1",
      "sport_key": "basketball_nba",
      "sport_title": "NBA",
      "commence_time": "2021-11-11T03:10:00Z",
      "home_team": "Los Angeles Lakers",
      "away_team": "Miami Heat"
    },
    {
      "id": "57b3a9115d008b937f7fa06d361e6ec9",
      "sport_key": "basketball_nba",
      "sport_title": "NBA",
      "commence_time": "2021-11-11T03:10:00Z",
      "home_team": "Golden State Warriors",
      "away_team": "Minnesota Timberwolves"
    },
    {
      "id": "9be419f9564743ef051e2f5a97398953",
      "sport_key": "basketball_nba",
      "sport_title": "NBA",
      "commence_time": "2021-11-11T00:40:00Z",
      "home_team": "Houston Rockets",
      "away_team": "Detroit Pistons"
    },
    {
      "id": "f10ec048aad85d3325fa3fc9f59c4125",
      "sport_key": "basketball_nba",
      "sport_title": "NBA",
      "commence_time": "2021-11-11T01:10:00Z",
      "home_team": "New Orleans Pelicans",
      "away_team": "Oklahoma City Thunder"
    },
    {
      "id": "bcddc0ecb1d1161c8ad9fcab9ffa2e66",
      "sport_key": "basketball_nba",
      "sport_title": "NBA",
      "commence_time": "2021-11-11T02:10:00Z",
      "home_team": "Phoenix Suns",
      "away_team": "Portland Trail Blazers"
    },
    {
      "id": "8475084d53ea5b67de53042c04677158",
      "sport_key": "basketball_nba",
      "sport_title": "NBA",
      "commence_time": "2021-11-11T02:10:00Z",
      "home_team": "Denver Nuggets",
      "away_team": "Indiana Pacers"
    }
  ]
}