{
  "timestamp": "2022-12-07T11:55:39Z",
  "previous_timestamp": "2022-12-07T11:50:38Z",
  "next_timestamp": "2022-12-07T12:00:39Z",
  "data": [
    {
      "id": "a7f4ba85571ca614d2720f2eec14b575",
      "sport_key": "basketball_nba",
      "sport_title": "NBA",
      "commence_time": "2022-12-08T00:10:00Z",
      "home_team": "Orlando Magic",
      "away_team": "Los Angeles Clippers"
    },
    {
      "id": "79b7ba43cfc5f8df4e76bae7b34549ab",
      "sport_key": "basketball_nba",
      "sport_title": "NBA",
      "commence_time": "2022-12-08T00:40:00Z",
      "home_team": "New York Knicks",
      "away_team": "Atlanta Hawks"
    },
    {
      "id": "3eacc15c1fe42f747d29ceedc29cda0b",
      "sport_key": "basketball_nba",
      "sport_title": "NBA",
      "commence_time": "2022-12-08T00:40:00Z",
      "home_team": "Brooklyn Nets",
      "away_team": "Charlotte Hornets"
    },
    {
      "id": "f1e2c289fb4231e53ef5c69aee6f9065",
      "sport_key": "basketball_nba",
      "sport_title": "NBA",
      "commence_time": "2022-12-08T00:40:00Z",
      "home_team": "Toronto Raptors",
      "away_team": "Los Angeles Lakers"
    },
    {
      "id": "3255c75fda5e557e09b233aa6f4d4af2",
      "sport_key": "basketball_nba",
      "sport_title": "NBA",
      "commence_time": "2022-12-08T01:10:00Z",
      "home_team": "Chicago Bulls",
      "away_team": "Washington Wizards"
    },
    {
      "id": "501b4c292c1cea36c8a909520ed4f57c",
      "sport_key": "basketball_nba",
      "sport_title": "NBA",
      "commence_time": "2022-12-08T01:10:00Z",
      "home_team": "New Orleans Pelicans",
      "away_team": "Detroit Pistons"
    },
    {
      "id": "6b53190b8ff9ba7e17415c36a0e29852",
      "sport_key": "basketball_nba",
      "sport_title": "NBA",
      "commence_time": "2022-12-08T01:10:00Z",
      "home_team": "Minnesota Timberwolves",
      "away_team": "Indiana Pacers"
    },
    {
      "id": "7d527cf1f0d2fe20c4144198bac8f51a",
      "sport_key": "basketball_nba",
      "sport_title": "NBA",
      "commence_time": "2022-12-08T01:10:00Z",
      "home_team": "Memphis Grizzlies",
      "away_team": "Oklahoma City Thunder"
    },
    {
      "id": "e7b96942cdb70011d34f5fe63971a91d",
      "sport_key": "basketball_nba",
      "sport_title": "NBA",
      "commence_time": "2022-12-08T01:10:00Z",
      "home_team": "Milwaukee Bucks",
      "away_team": "Sacramento Kings"
    },
    {
      "id": "3577b91efaf4322a7f4293bb0b0d576d",
      "sport_key": "basketball_nba",
      "sport_title": "NBA",
      "commence_time": "2022-12-08T02:10:00Z",
      "home_team": "Utah Jazz",
      "away_team": "Golden State Warriors"
    },
    {
      "id": "4b2377a35e47201f7561eb9a806e922a",
      "sport_key": "basketball_nba",
      "sport_title": "NBA",
      "commence_time": "2022-12-08T03:10:00Z",
      "home_team": "Phoenix Suns",
      "away_team": "Boston Celtics"
    }
  ]
}