{
  "timestamp": "2023-04-14T11:55:40Z",
  "previous_timestamp": "2023-04-14T11:50:40Z",
  "next_timestamp": "2023-04-14T12:00:40Z",
  "data": [
    {
      "id": "10fe0d2783ed072bb02bf02dc657d095",
      "sport_key": "basketball_nba",
      "sport_title": "NBA",
      "commence_time": "2023-04-14T23:00:00Z",
      "home_team": "Miami Heat",
      "away_team": "Chicago Bulls"
    },
    {
      "id": "ec3655396791dd35ba12a8da871e8a66",
      "sport_key": "basketball_nba",
      "sport_title": "NBA",
      "commence_time": "2023-04-15T01:30:00Z",
      "home_team": "Minnesota Timberwolves",
      "away_team": "Oklahoma City Thunder"
    },
    {
      "id": "75c2ded107b0de858f62891d627b96ac",
      "sport_key": "basketball_nba",
      "sport_title": "NBA",
      "commence_time": "2023-04-15T17:00:00Z",
      "home_team": "Philadelphia 76ers",
      "away_team": "Brooklyn Nets"
    },
    {
      "id": "b25851fe1ed9f752a559a1037596979b",
      "sport_key": "basketball_nba",
      "sport_title": "NBA",
      "commence_time": "2023-04-15T19:30:00Z",
      "home_team": "Boston Celtics",
      "away_team": "Atlanta Hawks"
    },
    {
      "id": "a090ffb13e578cd89d37e0d8a4462576",
      "sport_key": "basketball_nba",
      "sport_title": "NBA",
      "commence_time": "2023-04-15T22:00:00Z",
      "home_team": "Cleveland Cavaliers",
      "away_team": "New York Knicks"
    },
    {
      "id": "df4b9058abf350a556c9e373815dd8a3",
      "sport_key": "basketball_nba",
      "sport_title": "NBA",
      "commence_time": "2023-04-16T00:30:00Z",
      "home_team": "Sacramento Kings",
      "away_team": "Golden State Warriors"
    },
    {
      "id": "66bda038401129292e9ed8b39295c6a9",
      "sport_key": "basketball_nba",
      "sport_title": "NBA",
      "commence_time": "2023-04-16T19:00:00Z",
      "home_team": "Memphis Grizzlies",
      "away_team": "Los Angeles Lakers"
    },
    {
      "id": "9e2b7296c01fb6619f09334528eb21fd",
      "sport_key": "basketball_nba",
      "sport_title": "NBA",
      "commence_time": "2023-04-17T00:00:00Z",
      "home_team": "Phoenix Suns",
      "away_team": "Los Angeles Clippers"
    }
  ]
}